{
  "packages": [
    {
      "name": "AlgoBot",
      "maintainer": "Algobrix",
      "websiteURL": "http://www.algobrix.com",
      "email": "ofer@algobrix.com",
      "help": {"online": "https://github.com/watterott/ATmega328PB-Testing"},

      "platforms": [
        {
          "name": "Algobrix Boards",
          "architecture": "avr",
          "version": "0.1.0",
          "category": "contributed",
          "help": {"online": "https://github.com/Algobrix/arduino_algobot_board"},
          "url": "https://github.com/Algobrix/arduino_algobot_board/blob/master/algobot_pack_0.1.zip?raw=true",
		   "checksum": "SHA-256:E5A7CC95450CC4509139440C567EC31D4DDC59B43AB409A4B43CC980B8A053A4",
          "archiveFileName": "algobot_pack_0.1.zip",
          "size": "103351",
          "boards": [
            {"name": "AlgoBot"}
          ]
        }
        
      ],

      "tools": [
        {
        }
      ]
    }
  ]
}
